{
  "stagedHeat" : {
    "@UUID" : "7722f981-2e85-4c1f-97e9-a2bb67dac34c",
    "timeToStart" : -2209006500000,
    "category" : "Community IronPerson Heat",
    "heatID" : 2,
    "heatNumber" : 102,
    "hasStarted" : true,
    "actualStartTime" : 1582943805153,
    "teams" : {
      "2164" : {
        "@UUID" : "79efc6d4-1dcc-4102-a535-f1421816c682",
        "poolName" : "DIV Women's",
        "teamID" : 52880,
        "teamNumber" : 2164,
        "teamName" : "All A-Bohr-d!",
        "heats" : {
          "102" : "7722f981-2e85-4c1f-97e9-a2bb67dac34c"
        },
        "runs" : {
          "102" : {
            "@UUID" : "0c3f0085-2049-4c37-8a11-50ae70eed88c",
            "heatNumber" : 102,
            "finalTime" : null,
            "sitrep" : "DNS",
            "team" : "79efc6d4-1dcc-4102-a535-f1421816c682",
            "isDone" : false,
            "canUndo" : false,
            "runNumber" : {
              "teamNumber" : 2164,
              "heatNumber" : 102
            }
          }
        },
        "currentRun" : "0c3f0085-2049-4c37-8a11-50ae70eed88c",
        "teamUnit" : "SUS"
      },
      "2502" : {
        "@UUID" : "f0caaad4-a7a0-4c01-803c-0227b2ef7b59",
        "poolName" : "JFF SAT",
        "teamID" : 53029,
        "teamNumber" : 2502,
        "teamName" : "99 Sea Line",
        "heats" : {
          "102" : "7722f981-2e85-4c1f-97e9-a2bb67dac34c"
        },
        "runs" : {
          "102" : {
            "@UUID" : "e269e00d-38f0-4e00-88f5-55c2a3e97e00",
            "heatNumber" : 102,
            "finalTime" : null,
            "sitrep" : "NONE",
            "team" : "f0caaad4-a7a0-4c01-803c-0227b2ef7b59",
            "isDone" : false,
            "canUndo" : false,
            "runNumber" : {
              "teamNumber" : 2502,
              "heatNumber" : 102
            }
          }
        },
        "currentRun" : "e269e00d-38f0-4e00-88f5-55c2a3e97e00",
        "teamUnit" : "CWD"
      },
      "2171" : {
        "@UUID" : "0735542a-5a3c-49e3-94c4-45dfdf7db5eb",
        "poolName" : "Community CoRec",
        "teamID" : 53294,
        "teamNumber" : 2171,
        "teamName" : "Adrian's Kids",
        "heats" : {
          "102" : "7722f981-2e85-4c1f-97e9-a2bb67dac34c"
        },
        "runs" : {
          "102" : {
            "@UUID" : "d3e8dfb4-3217-46d7-83cb-eeed44786117",
            "heatNumber" : 102,
            "finalTime" : null,
            "sitrep" : "NONE",
            "team" : "0735542a-5a3c-49e3-94c4-45dfdf7db5eb",
            "isDone" : false,
            "canUndo" : false,
            "runNumber" : {
              "teamNumber" : 2171,
              "heatNumber" : 102
            }
          }
        },
        "currentRun" : "d3e8dfb4-3217-46d7-83cb-eeed44786117",
        "teamUnit" : "CTY"
      },
      "2108" : {
        "@UUID" : "bbe0182c-4362-4215-a6fa-ffd52e1ce149",
        "poolName" : "CWD CoRec",
        "teamID" : 52895,
        "teamNumber" : 2108,
        "teamName" : "4.0 GPA 1",
        "heats" : {
          "102" : "7722f981-2e85-4c1f-97e9-a2bb67dac34c"
        },
        "runs" : {
          "102" : {
            "@UUID" : "27cbc19a-6145-4852-b25b-bf2271f8f25a",
            "heatNumber" : 102,
            "finalTime" : null,
            "sitrep" : "NONE",
            "team" : "bbe0182c-4362-4215-a6fa-ffd52e1ce149",
            "isDone" : false,
            "canUndo" : false,
            "runNumber" : {
              "teamNumber" : 2108,
              "heatNumber" : 102
            }
          }
        },
        "currentRun" : "27cbc19a-6145-4852-b25b-bf2271f8f25a",
        "teamUnit" : "CWD"
      },
      "2143" : {
        "@UUID" : "021df425-d698-40bb-bad7-114e190023dd",
        "poolName" : "DIV CoRec",
        "teamID" : 52953,
        "teamNumber" : 2143,
        "teamName" : "???? Longest Boat Ever ????",
        "heats" : {
          "102" : "7722f981-2e85-4c1f-97e9-a2bb67dac34c"
        },
        "runs" : {
          "102" : {
            "@UUID" : "8b84fe61-de05-4b1f-a92b-43e1147b7484",
            "heatNumber" : 102,
            "finalTime" : null,
            "sitrep" : "NONE",
            "team" : "021df425-d698-40bb-bad7-114e190023dd",
            "isDone" : false,
            "canUndo" : false,
            "runNumber" : {
              "teamNumber" : 2143,
              "heatNumber" : 102
            }
          }
        },
        "currentRun" : "8b84fe61-de05-4b1f-a92b-43e1147b7484",
        "teamUnit" : "SUS"
      }
    }
  },
  "currentRuns" : {
    "2502-102" : "e269e00d-38f0-4e00-88f5-55c2a3e97e00",
    "2171-102" : "d3e8dfb4-3217-46d7-83cb-eeed44786117",
    "2108-102" : "27cbc19a-6145-4852-b25b-bf2271f8f25a",
    "2143-102" : "8b84fe61-de05-4b1f-a92b-43e1147b7484"
  },
  "stoppedRuns" : { },
  "finishedRuns" : {
    "2470--101" : {
      "@UUID" : "74b16492-f908-4f21-9dac-b9c274fbbd7d",
      "heatNumber" : 101,
      "finalTime" : {
        "millisecondOfSet" : 1744,
        "minutes" : 0,
        "seconds" : 1,
        "milliseconds" : 744,
        "startTime" : 1582943696075,
        "stopTime" : 1582943697819
      },
      "sitrep" : "NONE",
      "team" : {
        "@UUID" : "3d908ce6-86d1-4cbf-be3c-9c7c9ffe750b",
        "poolName" : "JFF SAT",
        "teamID" : 52799,
        "teamNumber" : 2470,
        "teamName" : "AcaBoat",
        "heats" : {
          "101" : {
            "@UUID" : "b210b9d2-45fa-4845-b47b-c04a489e6e7d",
            "timeToStart" : -2209006800000,
            "category" : "Community CoRec Heat",
            "heatID" : 1,
            "heatNumber" : 101,
            "hasStarted" : true,
            "actualStartTime" : 1582943696075,
            "teams" : {
              "2598" : {
                "@UUID" : "f48e8a58-4ee3-464e-8b3b-4d0cc070c91b",
                "poolName" : "JFF SUN",
                "teamID" : 52854,
                "teamNumber" : 2598,
                "teamName" : "99 B Line",
                "heats" : {
                  "101" : "b210b9d2-45fa-4845-b47b-c04a489e6e7d"
                },
                "runs" : {
                  "101" : {
                    "@UUID" : "87c50c24-72fb-42e8-9108-eb3bb00f9345",
                    "heatNumber" : 101,
                    "finalTime" : {
                      "millisecondOfSet" : 1879,
                      "minutes" : 0,
                      "seconds" : 1,
                      "milliseconds" : 879,
                      "startTime" : 1582943696075,
                      "stopTime" : 1582943697954
                    },
                    "sitrep" : "NONE",
                    "team" : "f48e8a58-4ee3-464e-8b3b-4d0cc070c91b",
                    "isDone" : true,
                    "canUndo" : false,
                    "runNumber" : {
                      "teamNumber" : 2598,
                      "heatNumber" : 101
                    }
                  }
                },
                "currentRun" : null,
                "teamUnit" : "CWD"
              },
              "2470" : "3d908ce6-86d1-4cbf-be3c-9c7c9ffe750b",
              "2471" : {
                "@UUID" : "8b31dc17-465d-414c-984c-3eb41ea9c9c1",
                "poolName" : "JFF SAT",
                "teamID" : 52798,
                "teamNumber" : 2471,
                "teamName" : "All a-Bohr-d",
                "heats" : {
                  "101" : "b210b9d2-45fa-4845-b47b-c04a489e6e7d"
                },
                "runs" : {
                  "101" : {
                    "@UUID" : "76b3594e-9be7-4ff7-b508-a21e94be2922",
                    "heatNumber" : 101,
                    "finalTime" : {
                      "millisecondOfSet" : 1609,
                      "minutes" : 0,
                      "seconds" : 1,
                      "milliseconds" : 609,
                      "startTime" : 1582943696075,
                      "stopTime" : 1582943697684
                    },
                    "sitrep" : "NONE",
                    "team" : "8b31dc17-465d-414c-984c-3eb41ea9c9c1",
                    "isDone" : true,
                    "canUndo" : false,
                    "runNumber" : {
                      "teamNumber" : 2471,
                      "heatNumber" : 101
                    }
                  }
                },
                "currentRun" : null,
                "teamUnit" : "CWD"
              },
              "2443" : {
                "@UUID" : "50267603-548c-4dc2-88dc-8e4e8f808c40",
                "poolName" : "JFF SAT",
                "teamID" : 52889,
                "teamNumber" : 2443,
                "teamName" : " Longboiz 2",
                "heats" : {
                  "101" : "b210b9d2-45fa-4845-b47b-c04a489e6e7d"
                },
                "runs" : {
                  "101" : {
                    "@UUID" : "bc4283ae-21c8-4613-915b-b5c254c25448",
                    "heatNumber" : 101,
                    "finalTime" : {
                      "millisecondOfSet" : 1463,
                      "minutes" : 0,
                      "seconds" : 1,
                      "milliseconds" : 463,
                      "startTime" : 1582943696075,
                      "stopTime" : 1582943697538
                    },
                    "sitrep" : "NONE",
                    "team" : "50267603-548c-4dc2-88dc-8e4e8f808c40",
                    "isDone" : true,
                    "canUndo" : false,
                    "runNumber" : {
                      "teamNumber" : 2443,
                      "heatNumber" : 101
                    }
                  }
                },
                "currentRun" : null,
                "teamUnit" : "CWD"
              },
              "2526" : {
                "@UUID" : "f5c3a113-fbaf-4e01-baaf-a2798dfa045f",
                "poolName" : "CWD CoRec",
                "teamID" : 53018,
                "teamNumber" : 2526,
                "teamName" : "2018 Survivors",
                "heats" : {
                  "101" : "b210b9d2-45fa-4845-b47b-c04a489e6e7d"
                },
                "runs" : {
                  "101" : {
                    "@UUID" : "8ac2f7d8-41b2-40d2-88d9-c16adad6e44d",
                    "heatNumber" : 101,
                    "finalTime" : {
                      "millisecondOfSet" : 1328,
                      "minutes" : 0,
                      "seconds" : 1,
                      "milliseconds" : 328,
                      "startTime" : 1582943696075,
                      "stopTime" : 1582943697403
                    },
                    "sitrep" : "NONE",
                    "team" : "f5c3a113-fbaf-4e01-baaf-a2798dfa045f",
                    "isDone" : true,
                    "canUndo" : false,
                    "runNumber" : {
                      "teamNumber" : 2526,
                      "heatNumber" : 101
                    }
                  }
                },
                "currentRun" : null,
                "teamUnit" : "CWD"
              }
            }
          }
        },
        "runs" : {
          "101" : "74b16492-f908-4f21-9dac-b9c274fbbd7d"
        },
        "currentRun" : null,
        "teamUnit" : "CWD"
      },
      "isDone" : true,
      "canUndo" : false,
      "runNumber" : {
        "teamNumber" : 2470,
        "heatNumber" : 101
      }
    },
    "2598--101" : "87c50c24-72fb-42e8-9108-eb3bb00f9345",
    "2526--101" : "8ac2f7d8-41b2-40d2-88d9-c16adad6e44d",
    "2443--101" : "bc4283ae-21c8-4613-915b-b5c254c25448",
    "2471--101" : "76b3594e-9be7-4ff7-b508-a21e94be2922"
  }
}